<?xml version="1.0" encoding="UTF-8" standalone="yes"?>






<channel>	



<item>
<title>Syria TV [COLOR=FF00FF00]HD[/COLOR]</title> 
<link>http://lv003.cdn03.greek.zaaptv.com:80/live/m3u8/SyriaCh.m3u8?__token__=ip=190.38.123.201~exp=1479597258~acl=/live/m3u8/SyriaCh.m3u8*~hmac=ed59a6d2ae6732dc52316866d82cb6ef220d71d5cfc17a6bfcab90a116ef0472</link>
<thumbnail>http://www.lyngsat-logo.com/logo/tv/ss/syria_satellite_channel.jpg</thumbnail>
</item>

<item>
<title>Syria Drama [COLOR=FF00FF00]HD[/COLOR]</title> 
<link>http://lv003.cdn03.greek.zaaptv.com:80/live/m3u8/syriadram.m3u8?__token__=ip=190.38.123.201~exp=1479597258~acl=/live/m3u8/syriadram.m3u8*~hmac=512795a43955cfa7ae1d4d1ad07c16fed7f56f16725e058ba1a9db3f9ce0d31c</link>
<thumbnail>http://www.lyngsat-logo.com/logo/tv/ss/syria_drama_channel.png</thumbnail>
</item>

<item>
<title>Sama [COLOR=FF00FF00]HD[/COLOR]</title> 
<link>http://lv003.cdn03.greek.zaaptv.com:80/live/m3u8/Samatv.m3u8?__token__=ip=190.38.123.201~exp=1479597258~acl=/live/m3u8/Samatv.m3u8*~hmac=39150fcb9b69036f6a18fef7837d9d06f39ca1ef7693bc79228f53c53ca73eb1</link>
<thumbnail>http://www.lyngsat-logo.com/logo/tv/ss/sama_tv.png</thumbnail>
</item>

<item>
<title>Sham FM [COLOR=FF00FF00]HD[/COLOR]</title> 
<link>http://lv001.cdn03.greek.zaaptv.com:80/live/m3u8/Sham.m3u8?__token__=ip=190.38.123.201~exp=1479597258~acl=/live/m3u8/Sham.m3u8*~hmac=89ac935a3e5b1c4ffcd47b4309ba67b4bf5c8a9606591b8e0dbc565fb44c1a23</link>
<thumbnail>http://www.pixentral.com/pics/1FWsvOPPlA2Y6Ucjlhoq8PxihNfY1.jpg</thumbnail>
</item>

<item>
<title>OTV Lebanon [COLOR=FF00FF00]HD[/COLOR]</title>
<link>http://lv004.cdn03.greek.zaaptv.com:80/live/m3u8/H7sKl3Sdx9238.m3u8?__token__=ip=190.38.123.201~exp=1479597258~acl=/live/m3u8/H7sKl3Sdx9238.m3u8*~hmac=d43a93ac3f4cc904c923ec9a11c0d76d32508808de533c4ed5f46e252cc983e7</link>
<thumbnail>http://www.lyngsat-logo.com/logo/tv/oo/otv_lb.jpg</thumbnail>
</item>


<item>
<title>Al Jadeed  [COLOR=FFFF0000]SD[/COLOR]</title>
<link>http://lv003.cdn03.greek.zaaptv.com:80/live/m3u8/H7sKl3Sdx9235.m3u8?__token__=ip=190.38.123.201~exp=1479597258~acl=/live/m3u8/H7sKl3Sdx9235.m3u8*~hmac=91a927cfdd6993c172ea4655dba3bfe250baf378873b6b370e63a2525a60f57c</link>
<thumbnail>http://www.pixentral.com/pics/1PDtMQpSeV39pmgEmb6xstFc2YMO.jpg</thumbnail>
</item>


<item>
<title>LDC [COLOR=FF00FF00]HD[/COLOR]</title>
<link>http://lv003.cdn03.greek.zaaptv.com:80/live/m3u8/H7sKl3Sdx9218.m3u8?__token__=ip=190.38.123.201~exp=1479597258~acl=/live/m3u8/H7sKl3Sdx9218.m3u8*~hmac=19d472d149a0799e4796e49a95e3a8002604c1017e26cb341260fa18eadd3733</link>
<thumbnail>http://www.lyngsat-logo.com/logo/tv/ll/ldc_lb.jpg</thumbnail>
</item>

<item>
<title>LBC International [COLOR=FF00FF00]HD[/COLOR]</title>         
<link>http://lv004.cdn03.greek.zaaptv.com:80/live/m3u8/H7sKl3Sdx9217.m3u8?__token__=ip=190.38.123.201~exp=1479597258~acl=/live/m3u8/H7sKl3Sdx9217.m3u8*~hmac=dc272d027615ecba6c8e28b61d7d6953b8da3546225972132b592580013ecc2c</link>
<thumbnail>http://www.lyngsat-logo.com/logo/tv/ll/lbc_sat.jpg</thumbnail>
</item>


<item>
<title>MTV [COLOR=FF00FF00]HD[/COLOR]</title>
<link>http://lv003.cdn03.greek.zaaptv.com:80/live/m3u8/H7sKl3SdMtvL.m3u8?__token__=ip=190.38.123.201~exp=1479597258~acl=/live/m3u8/H7sKl3SdMtvL.m3u8*~hmac=36eb82d340bb4f63e073d6f3761c5e72886ffbcd94d3b9848a5b7e2d00023a55</link>
<thumbnail>http://www.lyngsat-logo.com/logo/tv/mm/murr_tv_lebanon.jpg</thumbnail>
</item>

<item>
<title>MTV 2 [COLOR=FF00FF00]HD[/COLOR]</title>
<link>http://ts001.cdn03.greek.zaaptv.com:80/timeshift/m3u8/H7sKl3SdMtvL_delayed_3600.m3u8?__token__=ip=190.38.123.201~exp=1479597258~acl=/timeshift/m3u8/H7sKl3SdMtvL_delayed_3600.m3u8*~hmac=fb975e9ef0d1619e65169e504bd4b077673d10656eba71ee85ecd95d33479c77</link>
<thumbnail>http://www.lyngsat-logo.com/logo/tv/mm/murr_tv_lebanon.jpg</thumbnail>
</item>
      
<item>
<title>Future [COLOR=FF00FF00]HD[/COLOR]</title>         
<link>http://lv004.cdn03.greek.zaaptv.com:80/live/m3u8/H7sKl3SdFutrI.m3u8?__token__=ip=190.38.123.201~exp=1479597258~acl=/live/m3u8/H7sKl3SdFutrI.m3u8*~hmac=c18e97f57239f828e67e00bb1bb717949ab6ab63f708b6ad994f86b142461343</link>
<thumbnail>http://www.lyngsat-logo.com/logo/tv/ff/future_tv_satellite.jpg</thumbnail>
</item>



<item>
<title>MBC 1 [COLOR=FF00FF00]HD[/COLOR]</title>         
<link>http://lv004.cdn03.greek.zaaptv.com:80/live/m3u8/H7sKl3Sdx9219.m3u8?__token__=ip=190.38.123.201~exp=1479597258~acl=/live/m3u8/H7sKl3Sdx9219.m3u8*~hmac=0ba81523d270fcf66fb68621a079bbcdea5a0293a6e3b7af236f3465c4fc4b98</link>
<thumbnail>http://www.lyngsat-logo.com/logo/tv/mm/mbc1.jpg</thumbnail>
</item>

<item>
<title>MBC 4 [COLOR=FF00FF00]HD[/COLOR]</title>         
<link>http://lv004.cdn03.greek.zaaptv.com:80/live/m3u8/H7sKl3Sdx9221.m3u8?__token__=ip=190.38.123.201~exp=1479597258~acl=/live/m3u8/H7sKl3Sdx9221.m3u8*~hmac=eef94c0df594ae0fc9814165d807c230cfde35590bdf1f24a050f24d7cd127c5</link>
<thumbnail>http://www.lyngsat-logo.com/logo/tv/mm/mbc4.jpg</thumbnail>
</item>

<item>
<title>MBC Drama [COLOR=FF00FF00]HD[/COLOR]</title>         
<link>http://lv004.cdn03.greek.zaaptv.com:80/live/m3u8H7sKl3Sdx9224.m3u8?__token__=ip=190.38.123.201~exp=1479597258~acl=/live/m3u8/H7sKl3Sdx9224.m3u8*~hmac=5a1cd1f93e3384ae0328d4dcb0b06e467b72cdf42af5e87d4387b0aa3d2fd9b6</link>
<thumbnail>http://www.lyngsat-logo.com/logo/tv/mm/mbc_plus_drama_hd.jpg</thumbnail>
</item>
      
<item>
<title>ARABICA [COLOR=FF00FF00]HD[/COLOR]</title> 
<link>http://ts001.cdn03.greek.zaaptv.com:80/timeshift/m3u8/arabica_delayed_2100.m3u8?__token__=ip=190.38.123.201~exp=1479597258~acl=/timeshift/m3u8/arabica_delayed_2100.m3u8*~hmac=bb317e3da9929ef181213c7bc978621afa7e97cf22099b2eb4ea59102c9019c6</link>
<thumbnail>http://www.lyngsat-logo.com/logo/tv/aa/arabica_music_tv.png</thumbnail>
</item>
      
<item>
<title>Rotana Clip [COLOR=FF00FF00]HD[/COLOR]</title>         
<link>http://lv004.cdn03.greek.zaaptv.com:80/live/m3u8/H7sKl3SdRotanaCp.m3u8?__token__=ip=190.38.123.201~exp=1479597258~acl=/live/m3u8/H7sKl3SdRotanaCp.m3u8*~hmac=041502483be50e89e342bc594a7a3ab8f7f90adb97c91998e96b21aed9dc3743</link>
<thumbnail>http://www.lyngsat-logo.com/logo/tv/rr/rotana_clip.jpg</thumbnail>
</item>
      
</channel>
