<?xml version="1.0" encoding="UTF-8" standalone="yes"?>






<channel>	

  
<item>
<title>FARIHA 14</title>
<link>http://vod-a.nl.panet.co.il/vod/256/256573/256573.mp4?md5=C4IW10zUx_3-KQjoWMoCIw&amp;expires=1481088029</link>
<thumbnail>http://pms.panet.co.il/online/images/video_lib/17/17_257338_thumb_20160905100055.jpg</thumbnail>
</item>

<item>
<title>FARIHA 15</title>
<link>http://vod-a.nl.panet.co.il/vod/257/257336/257336.mp4?md5=FZKyAR0cQrUz0uI9Cwz6rQ&amp;expires=1481089366</link>
<thumbnail>http://pms.panet.co.il/online/images/video_lib/17/17_257338_thumb_20160905100055.jpg</thumbnail>
</item>
  
<item>
<title>FARIHA 16</title>
<link>http://vod-a.nl.panet.co.il/vod/257/257338/257338.mp4?md5=j0PS-HunwmODHn_HdrHicw&amp;expires=1481089364</link>
<thumbnail>http://pms.panet.co.il/online/images/video_lib/17/17_257338_thumb_20160905100055.jpg</thumbnail>
</item>
  
<item>
<title>FARIHA 17</title>
<link>http://vod-a.nl.panet.co.il/vod/257/257552/257552.mp4?md5=rdeU6SnBCIMlxkJGgNnNBA&amp;expires=1481089402</link>
<thumbnail>http://pms.panet.co.il/online/images/video_lib/17/17_257338_thumb_20160905100055.jpg</thumbnail>
</item>
  
  
</channel>	
