<?xml version="1.0" encoding="UTF-8" standalone="yes"?>






<channel>	


  
<item>
<title>Fariha 48</title>
<link>http://vod-a.nl.panet.co.il/vod/266/266272/266272.mp4?md5=QMkIzoXcz_7is9q-Vqlg9A&amp;expires=1484371343</link>
<thumbnail>http://pms.panet.co.il/online/images/video_lib/17/17_264986_thumb_20161014145105.jpg</thumbnail>
</item>

 <item>
<title>Fariha 49</title>
<link>http://vod-a.nl.panet.co.il/vod/266/266544/266544.mp4?md5=H4PWfNmeUoe-KdgmxUeddA&amp;expires=1484371179</link>
<thumbnail>http://pms.panet.co.il/online/images/video_lib/17/17_264986_thumb_20161014145105.jpg</thumbnail>
</item>
  
  <item>
<title>Fariha 50</title>
<link>http://vod-a.nl.panet.co.il/vod/267/267009/267009.mp4?md5=9fM49S0FgVGiwUSHs0zBdA&amp;expires=1484371433</link>
<thumbnail>http://pms.panet.co.il/online/images/video_lib/17/17_264986_thumb_20161014145105.jpg</thumbnail>
</item>

    <item>
<title>Fariha 51</title>
<link>http://vod-a.nl.panet.co.il/vod/267/267264/267264.mp4?md5=uQUeUOJzpAJ6xjGwTtxYQQ&amp;expires=1484371458</link>
<thumbnail>http://pms.panet.co.il/online/images/video_lib/17/17_264986_thumb_20161014145105.jpg</thumbnail>
</item>
  
      <item>
<title>Fariha 52</title>
<link>http://vod-a.nl.panet.co.il/vod/267/267564/267564.mp4?md5=YpWn2ihu60Yt62FVPWFkOQ&amp;expires=1484371488</link>
<thumbnail>http://pms.panet.co.il/online/images/video_lib/17/17_264986_thumb_20161014145105.jpg</thumbnail>
</item>
  
</channel>	
